yuenpycounts/__init__.py
yuenpycounts/plotting.py
yuenpycounts/yuenpycounts.py
yuenpycounts-0.1.16.dist-info/LICENSE
yuenpycounts-0.1.16.dist-info/METADATA
yuenpycounts-0.1.16.dist-info/WHEEL
yuenpycounts-0.1.16.dist-info/RECORD
