Metadata-Version: 2.1
Name: yuenpycounts
Version: 0.1.16
Summary: Calculate word counts in a text file!
License: MIT
Author: Micheal
Requires-Python: >=3.9,<4.0
Classifier: License :: OSI Approved :: MIT License
Classifier: Programming Language :: Python :: 3
Classifier: Programming Language :: Python :: 3.9
Classifier: Programming Language :: Python :: 3.10
Classifier: Programming Language :: Python :: 3.11
Requires-Dist: matplotlib (>=3.7.2,<4.0.0)
